{
  "last_updated": "2026-04-29",
  "active_task": "task_2026-04-13_v3_3_logic_and_data_view_alignment.md",
  "owner": "未分配",
  "status": "in_progress",
  "dual_review_gate": "not_run",
  "current_focus": [
    "基线模板剥离计划已执行完毕，产物验证通过",
    "当前进入自动化Pipeline实现阶段"
  ],
  "recent_completed": [
    "基线模板剥离完成：生成 templates/Collection_Operations_Report_base.html，修复 tl-connect-gap 锚点，产物验证全部9个补丁元素各恰好出现1次",
    "阶段一完成：清理4-21污染模板（Data View/TL View/STL View重复模块去重）",
    "根因定位：脚本补丁逻辑非幂等，4-21模板保留单次补丁产物导致二次叠加"
  ],
  "next_actions": [
    "【P1】实现 get_write_data_from_dataworks.py（本地run_sql替换）",
    "【P2】编写 run_pipeline.py（取数→生成HTML→分发）",
    "【P3】Windows Task Scheduler 定时配置",
    "【P4/长期】Jinja2 模板迁移",
    "【P5/长期】Agent 级精准诊断"
  ],
  "blockers": [
    "Function Compute HTTP API 认证方式未确认（需 AccessKey + Bearer Token 测试）"
  ],
  "open_questions": [
    "容忍带数值（attendance 2pp / connect 5pp / loss 5pp / dial 10%）是否需要根据实际数据调参？",
    "自动化产物分发方式：企微 / 邮件 / 云盘？"
  ]
}
